<?xml version="1.0" encoding="UTF-8"?>
<!DOCTYPE plist PUBLIC "-//Apple Computer//DTD PLIST 1.0//EN" "http://www.apple.com/DTDs/PropertyList-1.0.dtd">
<plist version="1.0">
    <dict>
        <key>frames</key>
        <dict>
            <key>battle/cast01.png</key>
            <dict>
                <key>frame</key>
                <string>{{2,2},{60,90}}</string>
                <key>offset</key>
                <string>{0,0}</string>
                <key>rotated</key>
                <false/>
                <key>sourceColorRect</key>
                <string>{{0,0},{60,90}}</string>
                <key>sourceSize</key>
                <string>{60,90}</string>
            </dict>
            <key>battle/cast02.png</key>
            <dict>
                <key>frame</key>
                <string>{{64,2},{60,90}}</string>
                <key>offset</key>
                <string>{0,0}</string>
                <key>rotated</key>
                <false/>
                <key>sourceColorRect</key>
                <string>{{0,0},{60,90}}</string>
                <key>sourceSize</key>
                <string>{60,90}</string>
            </dict>
            <key>battle/cast03.png</key>
            <dict>
                <key>frame</key>
                <string>{{126,2},{60,90}}</string>
                <key>offset</key>
                <string>{0,0}</string>
                <key>rotated</key>
                <false/>
                <key>sourceColorRect</key>
                <string>{{0,0},{60,90}}</string>
                <key>sourceSize</key>
                <string>{60,90}</string>
            </dict>
            <key>battle/cast04.png</key>
            <dict>
                <key>frame</key>
                <string>{{188,2},{60,90}}</string>
                <key>offset</key>
                <string>{0,0}</string>
                <key>rotated</key>
                <false/>
                <key>sourceColorRect</key>
                <string>{{0,0},{60,90}}</string>
                <key>sourceSize</key>
                <string>{60,90}</string>
            </dict>
            <key>battle/cast05.png</key>
            <dict>
                <key>frame</key>
                <string>{{2,94},{61,90}}</string>
                <key>offset</key>
                <string>{0,0}</string>
                <key>rotated</key>
                <false/>
                <key>sourceColorRect</key>
                <string>{{0,0},{61,90}}</string>
                <key>sourceSize</key>
                <string>{61,90}</string>
            </dict>
            <key>battle/cast06.png</key>
            <dict>
                <key>frame</key>
                <string>{{65,94},{60,90}}</string>
                <key>offset</key>
                <string>{0,0}</string>
                <key>rotated</key>
                <false/>
                <key>sourceColorRect</key>
                <string>{{0,0},{60,90}}</string>
                <key>sourceSize</key>
                <string>{60,90}</string>
            </dict>
            <key>battle/rest01.png</key>
            <dict>
                <key>frame</key>
                <string>{{127,94},{70,90}}</string>
                <key>offset</key>
                <string>{0,0}</string>
                <key>rotated</key>
                <false/>
                <key>sourceColorRect</key>
                <string>{{0,0},{70,90}}</string>
                <key>sourceSize</key>
                <string>{70,90}</string>
            </dict>
            <key>battle/rest02.png</key>
            <dict>
                <key>frame</key>
                <string>{{2,186},{70,90}}</string>
                <key>offset</key>
                <string>{0,0}</string>
                <key>rotated</key>
                <false/>
                <key>sourceColorRect</key>
                <string>{{0,0},{70,90}}</string>
                <key>sourceSize</key>
                <string>{70,90}</string>
            </dict>
            <key>battle/rest03.png</key>
            <dict>
                <key>frame</key>
                <string>{{74,186},{70,90}}</string>
                <key>offset</key>
                <string>{0,0}</string>
                <key>rotated</key>
                <false/>
                <key>sourceColorRect</key>
                <string>{{0,0},{70,90}}</string>
                <key>sourceSize</key>
                <string>{70,90}</string>
            </dict>
            <key>battle/rest04.png</key>
            <dict>
                <key>frame</key>
                <string>{{146,186},{70,90}}</string>
                <key>offset</key>
                <string>{0,0}</string>
                <key>rotated</key>
                <false/>
                <key>sourceColorRect</key>
                <string>{{0,0},{70,90}}</string>
                <key>sourceSize</key>
                <string>{70,90}</string>
            </dict>
            <key>battle/rest05.png</key>
            <dict>
                <key>frame</key>
                <string>{{2,278},{70,90}}</string>
                <key>offset</key>
                <string>{0,0}</string>
                <key>rotated</key>
                <false/>
                <key>sourceColorRect</key>
                <string>{{0,0},{70,90}}</string>
                <key>sourceSize</key>
                <string>{70,90}</string>
            </dict>
            <key>battle/rest06.png</key>
            <dict>
                <key>frame</key>
                <string>{{74,278},{70,90}}</string>
                <key>offset</key>
                <string>{0,0}</string>
                <key>rotated</key>
                <false/>
                <key>sourceColorRect</key>
                <string>{{0,0},{70,90}}</string>
                <key>sourceSize</key>
                <string>{70,90}</string>
            </dict>
            <key>battle/rest07.png</key>
            <dict>
                <key>frame</key>
                <string>{{146,278},{70,90}}</string>
                <key>offset</key>
                <string>{0,0}</string>
                <key>rotated</key>
                <false/>
                <key>sourceColorRect</key>
                <string>{{0,0},{70,90}}</string>
                <key>sourceSize</key>
                <string>{70,90}</string>
            </dict>
            <key>battle/rest08.png</key>
            <dict>
                <key>frame</key>
                <string>{{2,370},{70,90}}</string>
                <key>offset</key>
                <string>{0,0}</string>
                <key>rotated</key>
                <false/>
                <key>sourceColorRect</key>
                <string>{{0,0},{70,90}}</string>
                <key>sourceSize</key>
                <string>{70,90}</string>
            </dict>
        </dict>
        <key>metadata</key>
        <dict>
            <key>format</key>
            <integer>2</integer>
            <key>realTextureFileName</key>
            <string>imp.png</string>
            <key>size</key>
            <string>{256,512}</string>
            <key>smartupdate</key>
            <string>$TexturePacker:SmartUpdate:aad1374b814bc0fc64f568d3c18d03d6$</string>
            <key>textureFileName</key>
            <string>imp.png</string>
        </dict>
    </dict>
</plist>
