<?xml version="1.0" encoding="UTF-8"?>
<!DOCTYPE plist PUBLIC "-//Apple Computer//DTD PLIST 1.0//EN" "http://www.apple.com/DTDs/PropertyList-1.0.dtd">
<plist version="1.0">
    <dict>
        <key>frames</key>
        <dict>
            <key>battle/cast01.png</key>
            <dict>
                <key>frame</key>
                <string>{{2,2},{120,120}}</string>
                <key>offset</key>
                <string>{0,0}</string>
                <key>rotated</key>
                <false/>
                <key>sourceColorRect</key>
                <string>{{0,0},{120,120}}</string>
                <key>sourceSize</key>
                <string>{120,120}</string>
            </dict>
            <key>battle/cast02.png</key>
            <dict>
                <key>frame</key>
                <string>{{124,2},{120,120}}</string>
                <key>offset</key>
                <string>{0,0}</string>
                <key>rotated</key>
                <false/>
                <key>sourceColorRect</key>
                <string>{{0,0},{120,120}}</string>
                <key>sourceSize</key>
                <string>{120,120}</string>
            </dict>
            <key>battle/cast03.png</key>
            <dict>
                <key>frame</key>
                <string>{{246,2},{120,120}}</string>
                <key>offset</key>
                <string>{0,0}</string>
                <key>rotated</key>
                <false/>
                <key>sourceColorRect</key>
                <string>{{0,0},{120,120}}</string>
                <key>sourceSize</key>
                <string>{120,120}</string>
            </dict>
            <key>battle/cast04.png</key>
            <dict>
                <key>frame</key>
                <string>{{368,2},{140,120}}</string>
                <key>offset</key>
                <string>{0,0}</string>
                <key>rotated</key>
                <false/>
                <key>sourceColorRect</key>
                <string>{{0,0},{140,120}}</string>
                <key>sourceSize</key>
                <string>{140,120}</string>
            </dict>
            <key>battle/cast05.png</key>
            <dict>
                <key>frame</key>
                <string>{{2,124},{150,119}}</string>
                <key>offset</key>
                <string>{0,0}</string>
                <key>rotated</key>
                <false/>
                <key>sourceColorRect</key>
                <string>{{0,0},{150,119}}</string>
                <key>sourceSize</key>
                <string>{150,119}</string>
            </dict>
            <key>battle/cast06.png</key>
            <dict>
                <key>frame</key>
                <string>{{154,124},{150,119}}</string>
                <key>offset</key>
                <string>{0,0}</string>
                <key>rotated</key>
                <false/>
                <key>sourceColorRect</key>
                <string>{{0,0},{150,119}}</string>
                <key>sourceSize</key>
                <string>{150,119}</string>
            </dict>
            <key>battle/cast07.png</key>
            <dict>
                <key>frame</key>
                <string>{{306,124},{150,119}}</string>
                <key>offset</key>
                <string>{0,0}</string>
                <key>rotated</key>
                <false/>
                <key>sourceColorRect</key>
                <string>{{0,0},{150,119}}</string>
                <key>sourceSize</key>
                <string>{150,119}</string>
            </dict>
            <key>battle/cast08.png</key>
            <dict>
                <key>frame</key>
                <string>{{2,245},{150,119}}</string>
                <key>offset</key>
                <string>{0,0}</string>
                <key>rotated</key>
                <false/>
                <key>sourceColorRect</key>
                <string>{{0,0},{150,119}}</string>
                <key>sourceSize</key>
                <string>{150,119}</string>
            </dict>
            <key>battle/rest01.png</key>
            <dict>
                <key>frame</key>
                <string>{{154,245},{130,110}}</string>
                <key>offset</key>
                <string>{0,0}</string>
                <key>rotated</key>
                <false/>
                <key>sourceColorRect</key>
                <string>{{0,0},{130,110}}</string>
                <key>sourceSize</key>
                <string>{130,110}</string>
            </dict>
            <key>battle/rest02.png</key>
            <dict>
                <key>frame</key>
                <string>{{286,245},{130,110}}</string>
                <key>offset</key>
                <string>{0,0}</string>
                <key>rotated</key>
                <false/>
                <key>sourceColorRect</key>
                <string>{{0,0},{130,110}}</string>
                <key>sourceSize</key>
                <string>{130,110}</string>
            </dict>
            <key>battle/rest03.png</key>
            <dict>
                <key>frame</key>
                <string>{{2,366},{130,110}}</string>
                <key>offset</key>
                <string>{0,0}</string>
                <key>rotated</key>
                <false/>
                <key>sourceColorRect</key>
                <string>{{0,0},{130,110}}</string>
                <key>sourceSize</key>
                <string>{130,110}</string>
            </dict>
            <key>battle/rest04.png</key>
            <dict>
                <key>frame</key>
                <string>{{134,366},{130,110}}</string>
                <key>offset</key>
                <string>{0,0}</string>
                <key>rotated</key>
                <false/>
                <key>sourceColorRect</key>
                <string>{{0,0},{130,110}}</string>
                <key>sourceSize</key>
                <string>{130,110}</string>
            </dict>
            <key>battle/rest05.png</key>
            <dict>
                <key>frame</key>
                <string>{{266,366},{130,110}}</string>
                <key>offset</key>
                <string>{0,0}</string>
                <key>rotated</key>
                <false/>
                <key>sourceColorRect</key>
                <string>{{0,0},{130,110}}</string>
                <key>sourceSize</key>
                <string>{130,110}</string>
            </dict>
        </dict>
        <key>metadata</key>
        <dict>
            <key>format</key>
            <integer>2</integer>
            <key>realTextureFileName</key>
            <string>sropho.png</string>
            <key>size</key>
            <string>{512,512}</string>
            <key>smartupdate</key>
            <string>$TexturePacker:SmartUpdate:d90b8b48efbc734df377027fc110ac48$</string>
            <key>textureFileName</key>
            <string>sropho.png</string>
        </dict>
    </dict>
</plist>
